{
"meta":{"test_sets":[],"test_metrics":[],"learn_metrics":[{"best_value":"Min","name":"Logloss"}],"launch_mode":"Train","parameters":"","iteration_count":10,"learn_sets":["learn"],"name":"experiment"},
"iterations":[
{"learn":[0.3023511524],"iteration":0,"passed_time":0.00274446955,"remaining_time":0.02470022595},
{"learn":[0.1766989002],"iteration":1,"passed_time":0.003589508528,"remaining_time":0.01435803411},
{"learn":[0.1198760098],"iteration":2,"passed_time":0.004380494603,"remaining_time":0.01022115407},
{"learn":[0.1025775424],"iteration":3,"passed_time":0.005128279118,"remaining_time":0.007692418677},
{"learn":[0.08086602425],"iteration":4,"passed_time":0.005879172179,"remaining_time":0.005879172179},
{"learn":[0.06864031551],"iteration":5,"passed_time":0.006683418149,"remaining_time":0.004455612099},
{"learn":[0.05773312952],"iteration":6,"passed_time":0.007503450659,"remaining_time":0.003215764568},
{"learn":[0.05119673668],"iteration":7,"passed_time":0.008350443907,"remaining_time":0.002087610977},
{"learn":[0.04383378817],"iteration":8,"passed_time":0.009116485419,"remaining_time":0.001012942824},
{"learn":[0.03986501157],"iteration":9,"passed_time":0.009958491088,"remaining_time":0}
]}